bnf_sampler-0.3.5.dist-info/METADATA
bnf_sampler-0.3.5.dist-info/WHEEL
bnf_sampler/__init__.py
bnf_sampler/bnf_sampler.pyd
bnf_sampler-0.3.5.dist-info/RECORD
