Metadata-Version: 2.1
Name: bnf_sampler
Version: 0.3.5
Summary: A crate that uses recursive descent algorithm to ensure tokens produced by a large language model follow a Backus Naur Form schema.
License: MIT OR Apache-2.0
Project-URL: Source Code, https://github.com/Dan-wanna-M/bnf_sampler
